setup.py
cassandra_snapshotter/__init__.py
cassandra_snapshotter/agent.py
cassandra_snapshotter/logging_helper.py
cassandra_snapshotter/main.py
cassandra_snapshotter/snapshotting.py
cassandra_snapshotter/timeout.py
cassandra_snapshotter/utils.py
cassandra_snapshotter.egg-info/PKG-INFO
cassandra_snapshotter.egg-info/SOURCES.txt
cassandra_snapshotter.egg-info/dependency_links.txt
cassandra_snapshotter.egg-info/entry_points.txt
cassandra_snapshotter.egg-info/not-zip-safe
cassandra_snapshotter.egg-info/pbr.json
cassandra_snapshotter.egg-info/requires.txt
cassandra_snapshotter.egg-info/top_level.txt