Metadata-Version: 1.1
Name: cassandra-snapshotter
Version: 0.5.0
Summary: Cassandra snapshotter is a tool to backup cassandra to Amazon S3.
Home-page: http://github.com/tbarbugli/cassandra_snapshotter
Author: Tommaso Barbugli
Author-email: tbarbugli@gmail.com
License: UNKNOWN
Platform: UNKNOWN
Classifier: Intended Audience :: Developers
Classifier: Intended Audience :: System Administrators
Classifier: Operating System :: OS Independent
Classifier: Topic :: Software Development
Classifier: Development Status :: 5 - Production/Stable
Classifier: License :: OSI Approved :: GNU General Public License (GPL)
Classifier: Natural Language :: English
Classifier: Programming Language :: Python
Classifier: Topic :: Scientific/Engineering :: Mathematics
Classifier: Topic :: Software Development :: Libraries :: Python Modules
